image_processing_clahe/__init__.py
image_processing_clahe/algoritmo.py
image_processing_clahe-0.0.3.dist-info/METADATA
image_processing_clahe-0.0.3.dist-info/WHEEL
image_processing_clahe-0.0.3.dist-info/top_level.txt
image_processing_clahe-0.0.3.dist-info/RECORD
