Metadata-Version: 2.1
Name: image-processing-clahe
Version: 0.0.3
Summary: Algoritmo de processamento de imagens CLAHE (Contrast Limited Adaptive Histogram Equalization).
Home-page: https://github.com/lucenarapereira/Portfolio-Engenharia-de-Dados/tree/main/Projeto%201/image-processing-package
Author: lucenara_pereira
Author-email: lucenarapereira@gmail.com
Requires-Python: >=3.8
Requires-Dist: opencv-python
Requires-Dist: matplotlib
